bertcc/__init__.py
bertcc/__main__.py
bertcc/converter.py
bertcc/utils/STCharacters.txt
bertcc/utils/STPhrases.txt
bertcc/utils/TWVariants.txt
bertcc/utils/__init__.py
bertcc/utils/constants.py
BertCC-0.1.0.dist-info/LICENSE
BertCC-0.1.0.dist-info/METADATA
BertCC-0.1.0.dist-info/WHEEL
BertCC-0.1.0.dist-info/entry_points.txt
BertCC-0.1.0.dist-info/top_level.txt
BertCC-0.1.0.dist-info/RECORD
