Metadata-Version: 2.1
Name: BertCC
Version: 0.1.0
Summary: A context-aware Simplified to Traditional Chinese converter using BERT
Home-page: https://github.com/Benau/BertCC
License: Apache License 2.0
Classifier: Development Status :: 5 - Production/Stable
Classifier: Intended Audience :: Developers
Classifier: Intended Audience :: Science/Research
Classifier: Programming Language :: Python :: 3
Classifier: License :: OSI Approved :: Apache Software License
Classifier: Operating System :: OS Independent
License-File: LICENSE
Requires-Dist: setuptools
Requires-Dist: torch
Requires-Dist: transformers
